{
	"groups": [
		{
			"keys": "l1_json,e2_png,e3_png,e4_png,e0_png,e1_png,grid_png,road_png,enemyConfig_json,e09_png,allColor_png,s1e0_png,s1e1_png,s1e2_png,s1e3_png,s1e4_png,s2e0_png,s2e1_png,s2e2_png,s2e3_png,s2e4_png,s3e0_png,s3e1_png,s3e2_png,s3e3_png,s3e4_png,menu_png,scroe_png,table1_png,toptable_png,wave_png,yuan_png,Clock Tick_wav,Whop_mp3,Wrong Move_mp3,1_wav,bgm_mp3,life_png,life_black_png,life_white_png,safety_png,start_png,tips_png,bird_png,main_button_png,planB_png,l2_json,e03_png,e00_png,e04_png,e02_png,e01_png,l3_json,l4_json,l5_json,prop3_png,prop4_png,prop5_png,prop1_png,prop2_png,yuan2_png,energy_png",
			"name": "preload"
		}
	],
	"resources": [
		{
			"name": "l1_json",
			"type": "json",
			"url": "res/l1.json"
		},
		{
			"name": "e2_png",
			"type": "image",
			"url": "assets/e2.png"
		},
		{
			"name": "e3_png",
			"type": "image",
			"url": "assets/e3.png"
		},
		{
			"name": "e4_png",
			"type": "image",
			"url": "assets/e4.png"
		},
		{
			"name": "e0_png",
			"type": "image",
			"url": "assets/e0.png"
		},
		{
			"name": "e1_png",
			"type": "image",
			"url": "assets/e1.png"
		},
		{
			"name": "grid_png",
			"type": "image",
			"url": "assets/grid.png"
		},
		{
			"name": "road_png",
			"type": "image",
			"url": "assets/road.png"
		},
		{
			"name": "enemyConfig_json",
			"type": "json",
			"url": "res/enemyConfig.json"
		},
		{
			"name": "e09_png",
			"type": "image",
			"url": "assets/e09.png"
		},
		{
			"name": "allColor_png",
			"type": "image",
			"url": "assets/allColor.png"
		},
		{
			"name": "s1e0_png",
			"type": "image",
			"url": "assets/s1e0.png"
		},
		{
			"name": "s1e1_png",
			"type": "image",
			"url": "assets/s1e1.png"
		},
		{
			"name": "s1e2_png",
			"type": "image",
			"url": "assets/s1e2.png"
		},
		{
			"name": "s1e3_png",
			"type": "image",
			"url": "assets/s1e3.png"
		},
		{
			"name": "s1e4_png",
			"type": "image",
			"url": "assets/s1e4.png"
		},
		{
			"name": "s2e0_png",
			"type": "image",
			"url": "assets/s2e0.png"
		},
		{
			"name": "s2e1_png",
			"type": "image",
			"url": "assets/s2e1.png"
		},
		{
			"name": "s2e2_png",
			"type": "image",
			"url": "assets/s2e2.png"
		},
		{
			"name": "s2e3_png",
			"type": "image",
			"url": "assets/s2e3.png"
		},
		{
			"name": "s2e4_png",
			"type": "image",
			"url": "assets/s2e4.png"
		},
		{
			"name": "s3e0_png",
			"type": "image",
			"url": "assets/s3e0.png"
		},
		{
			"name": "s3e1_png",
			"type": "image",
			"url": "assets/s3e1.png"
		},
		{
			"name": "s3e2_png",
			"type": "image",
			"url": "assets/s3e2.png"
		},
		{
			"name": "s3e3_png",
			"type": "image",
			"url": "assets/s3e3.png"
		},
		{
			"name": "s3e4_png",
			"type": "image",
			"url": "assets/s3e4.png"
		},
		{
			"name": "menu_png",
			"type": "image",
			"url": "assets/UI/menu.png"
		},
		{
			"name": "scroe_png",
			"type": "image",
			"url": "assets/UI/scroe.png"
		},
		{
			"name": "table1_png",
			"type": "image",
			"url": "assets/UI/table1.png"
		},
		{
			"name": "toptable_png",
			"type": "image",
			"url": "assets/UI/toptable.png"
		},
		{
			"name": "wave_png",
			"type": "image",
			"url": "assets/UI/wave.png"
		},
		{
			"name": "yuan_png",
			"type": "image",
			"url": "assets/UI/yuan.png"
		},
		{
			"name": "Clock Tick_wav",
			"type": "sound",
			"url": "assets/sound/Clock Tick.wav"
		},
		{
			"name": "Whop_mp3",
			"type": "sound",
			"url": "assets/sound/Whop.mp3"
		},
		{
			"name": "Wrong Move_mp3",
			"type": "sound",
			"url": "assets/sound/Wrong Move.mp3"
		},
		{
			"name": "1_wav",
			"type": "sound",
			"url": "assets/sound/1.wav"
		},
		{
			"name": "bgm_mp3",
			"type": "sound",
			"url": "assets/sound/bgm.mp3"
		},
		{
			"name": "life_png",
			"type": "image",
			"url": "assets/UI/life.png"
		},
		{
			"name": "life_black_png",
			"type": "image",
			"url": "assets/UI/life_black.png"
		},
		{
			"name": "life_white_png",
			"type": "image",
			"url": "assets/UI/life_white.png"
		},
		{
			"name": "safety_png",
			"type": "image",
			"url": "assets/UI/safety.png"
		},
		{
			"name": "start_png",
			"type": "image",
			"url": "assets/UI/start.png"
		},
		{
			"name": "tips_png",
			"type": "image",
			"url": "assets/UI/tips.png"
		},
		{
			"name": "bird_png",
			"type": "image",
			"url": "assets/UI/bird.png"
		},
		{
			"name": "main_button_png",
			"type": "image",
			"url": "assets/UI/main_button.png"
		},
		{
			"name": "planB_png",
			"type": "image",
			"url": "assets/UI/planB.png"
		},
		{
			"name": "l2_json",
			"type": "json",
			"url": "res/l2.json"
		},
		{
			"name": "e03_png",
			"type": "image",
			"url": "assets/e03.png"
		},
		{
			"name": "e00_png",
			"type": "image",
			"url": "assets/e00.png"
		},
		{
			"name": "e04_png",
			"type": "image",
			"url": "assets/e04.png"
		},
		{
			"name": "e02_png",
			"type": "image",
			"url": "assets/e02.png"
		},
		{
			"name": "e01_png",
			"type": "image",
			"url": "assets/e01.png"
		},
		{
			"name": "l3_json",
			"type": "json",
			"url": "res/l3.json"
		},
		{
			"name": "l4_json",
			"type": "json",
			"url": "res/l4.json"
		},
		{
			"name": "l5_json",
			"type": "json",
			"url": "res/l5.json"
		},
		{
			"name": "prop3_png",
			"type": "image",
			"url": "assets/UI/prop3.png"
		},
		{
			"name": "prop4_png",
			"type": "image",
			"url": "assets/UI/prop4.png"
		},
		{
			"name": "prop5_png",
			"type": "image",
			"url": "assets/UI/prop5.png"
		},
		{
			"name": "prop1_png",
			"type": "image",
			"url": "assets/UI/prop1.png"
		},
		{
			"name": "prop2_png",
			"type": "image",
			"url": "assets/UI/prop2.png"
		},
		{
			"name": "yuan2_png",
			"type": "image",
			"url": "assets/UI/yuan2.png"
		},
		{
			"name": "energy_png",
			"type": "image",
			"url": "assets/UI/energy.png"
		}
	]
}