{"mc":{
	"h1001":{
		"frameRate":12,
		"labels":[
			{"name":"idle","frame":1,"end":1}
			,{"name":"walking","frame":2,"end":5}
			,{"name":"walkingUp","frame":6,"end":9}
			,{"name":"walkingDown","frame":10,"end":13}
			,{"name":"fighting","frame":14,"end":18}
			,{"name":"dead","frame":19,"end":22}
			
			],
		"events":[
			
			],
		"frames":[
			
			{
			"res":"55ED99C2",
			"x":-27,
			"y":-37
			},
			{
			"res":"29A7C5A",
			"x":-27,
			"y":-37
			},
			{
			"res":"CA6487F3",
			"x":-27,
			"y":-37
			},
			{
			"res":"E586E65B",
			"x":-27,
			"y":-37
			},
			{
			"res":"76051CBF",
			"x":-27,
			"y":-37
			},
			{
			"res":"4F31F46C",
			"x":-27,
			"y":-37
			},
			{
			"res":"7DAEB08",
			"x":-27,
			"y":-37
			},
			{
			"res":"458C81FE",
			"x":-27,
			"y":-37
			},
			{
			"res":"379F1A84",
			"x":-27,
			"y":-37
			},
			{
			"res":"2C14B3B4",
			"x":-27,
			"y":-37
			},
			{
			"res":"AF22BEE2",
			"x":-27,
			"y":-37
			},
			{
			"res":"E7F8B02D",
			"x":-27,
			"y":-37
			},
			{
			"res":"F9A78F77",
			"x":-27,
			"y":-37
			},
			{
			"res":"26BFCBA4",
			"x":-27,
			"y":-37
			},
			{
			"res":"30546BCD",
			"x":-27,
			"y":-37
			},
			{
			"res":"1868B956",
			"x":-27,
			"y":-37
			},
			{
			"res":"A0442F43",
			"x":-27,
			"y":-37
			},
			{
			"res":"4ED96B9C",
			"x":-27,
			"y":-37
			},
			{
			"res":"EC6B9945",
			"x":-27,
			"y":-37
			},
			{
			"res":"112642F2",
			"x":-27,
			"y":-37
			},
			{
			"res":"8842325F",
			"x":-27,
			"y":-37
			},
			{
			"res":"B497D8C7",
			"x":-27,
			"y":-37
			}
			]
}},
	"res":{
		"55ED99C2":{"x":1,"y":1,"w":54,"h":44},
		"29A7C5A":{"x":57,"y":1,"w":54,"h":44},
		"CA6487F3":{"x":113,"y":1,"w":54,"h":44},
		"E586E65B":{"x":169,"y":1,"w":54,"h":44},
		"76051CBF":{"x":1,"y":47,"w":54,"h":44},
		"4F31F46C":{"x":57,"y":47,"w":54,"h":44},
		"7DAEB08":{"x":113,"y":47,"w":54,"h":44},
		"458C81FE":{"x":169,"y":47,"w":54,"h":44},
		"379F1A84":{"x":1,"y":93,"w":54,"h":44},
		"2C14B3B4":{"x":57,"y":93,"w":54,"h":44},
		"AF22BEE2":{"x":113,"y":93,"w":54,"h":44},
		"E7F8B02D":{"x":169,"y":93,"w":54,"h":44},
		"F9A78F77":{"x":1,"y":139,"w":54,"h":44},
		"26BFCBA4":{"x":57,"y":139,"w":54,"h":44},
		"30546BCD":{"x":113,"y":139,"w":54,"h":44},
		"1868B956":{"x":169,"y":139,"w":54,"h":44},
		"A0442F43":{"x":1,"y":185,"w":54,"h":44},
		"4ED96B9C":{"x":57,"y":185,"w":54,"h":44},
		"EC6B9945":{"x":113,"y":185,"w":54,"h":44},
		"112642F2":{"x":169,"y":185,"w":54,"h":44},
		"8842325F":{"x":1,"y":231,"w":54,"h":44},
		"B497D8C7":{"x":57,"y":231,"w":54,"h":44}
	}}